{
  "categories": [
    "5eca7b4c-7b4b-418c-9243-d23d3c425d03"
  ],
  "color": "#548488",
  "description": "",
  "mediaUuid": "b2ed2d94-5173-4ece-abbe-d89bb456b220",
  "subtitle": "",
  "skuCode": null,
  "tag": "path-game-score",
  "title": "Punteggi",
  "lastUpdate": "2021-12-03T15:59:10",
  "uuid": "8334f148-b941-48df-99e9-d1c0d1d9b477",
  "pathCategories": [
    {
      "color": null,
      "description": null,
      "lastUpdate": "2021-12-03T14:17:00",
      "mediaUuid": null,
      "order": 2,
      "subtitle": null,
      "tag": "secondary",
      "title": "I tuoi punteggi",
      "uuid": "5eca7b4c-7b4b-418c-9243-d23d3c425d03"
    }
  ],
  "mediaFiles": [
    {
      "lastUpdate": "2021-12-02T15:46:26",
      "mimeType": "image/png",
      "name": "test.png",
      "type": "IMG",
      "size": 31883,
      "url": "http://localhost:8080/wp-content/uploads/2021/11/test.png",
      "uuid": "b2ed2d94-5173-4ece-abbe-d89bb456b220"
    }
  ],
  "pois": [
    {
      "categories": [],
      "description": "",
      "mediaUuid": "b2ed2d94-5173-4ece-abbe-d89bb456b220",
      "subtitle": "",
      "tag": "poi-game-score",
      "title": "Punteggi",
      "lastUpdate": "2021-12-03T15:55:14",
      "uuid": "2a56d6ca-0604-4509-add7-a853020e828c"
    }
  ],
  "poiOrder": [
    {
      "index": 0,
      "isEnabled": true,
      "isVisited": true,
      "order": null,
      "poiUuid": "2a56d6ca-0604-4509-add7-a853020e828c",
      "isAccessibility": true,
      "isHidden": false,
      "id": 4
    }
  ],
  "poiCategories": [],
  "sheets": [
    {
      "description": null,
      "items": [],
      "lastUpdate": "2021-12-03T15:59:10",
      "mediaUuid": null,
      "subtitle": null,
      "title": "Punteggi",
      "tag": "poi-game-score-entry-sheet",
      "uuid": "c58afbf6-8b97-46ff-9bdd-dd85749f15b2"
    },
    {
      "description": "",
      "items": [
        "d5591c96-adcf-45f6-ad2c-d712f3ff6d94"
      ],
      "lastUpdate": "2021-12-03T15:55:05",
      "mediaUuid": "b2ed2d94-5173-4ece-abbe-d89bb456b220",
      "subtitle": "",
      "title": "Punteggi",
      "tag": "path-game-score-entry-sheet",
      "uuid": "efef25e5-c538-4571-a9aa-0768a00f3ed4"
    }
  ],
  "sheetItems": [
    {
      "lastUpdate": "2021-12-03T15:55:05",
      "order": 0,
      "uuid": "d5591c96-adcf-45f6-ad2c-d712f3ff6d94"
    }
  ],
  "relations": [
    {
      "poiUuid": "2a56d6ca-0604-4509-add7-a853020e828c",
      "inType": "SHT_ITM",
      "inUuid": "d5591c96-adcf-45f6-ad2c-d712f3ff6d94",
      "outType": "SHT",
      "outUuid": "c58afbf6-8b97-46ff-9bdd-dd85749f15b2"
    },
    {
      "poiUuid": "",
      "inUuid": "",
      "inType": "EPT",
      "outType": "SHT",
      "outUuid": "efef25e5-c538-4571-a9aa-0768a00f3ed4"
    }
  ],
  "totalSize": 31883
}